followit/LICENSE
followit/TODO.rst
followit/__init__.py
followit/compat.py
followit/models.py
followit/urls.py
followit/utils.py
followit/views.py
followit/migrations/0001_initial.py
followit/migrations/__init__.py
followit/tests/README.rst
followit/tests/__init__.py
followit/tests/manage.py
followit/tests/models.py
followit/tests/runtests.py
followit/tests/settings.py
followit/tests/tests.py
django_followit-0.4.1.dist-info/METADATA
django_followit-0.4.1.dist-info/WHEEL
django_followit-0.4.1.dist-info/top_level.txt
django_followit-0.4.1.dist-info/RECORD
