Metadata-Version: 2.1
Name: django-followit
Version: 0.4.1
Summary: A Django application that allows users to follow django model objects
Home-page: https://github.com/ASKBOT/django-followit
Author: Evgeny.Fadeev
Author-email: evgeny.fadeev@gmail.com
License: BSD License
Keywords: follow,database,django
Platform: UNKNOWN
Classifier: Development Status :: 4 - Beta
Classifier: Environment :: Web Environment
Classifier: Framework :: Django
Classifier: Intended Audience :: Developers
Classifier: License :: OSI Approved :: BSD License
Classifier: Operating System :: OS Independent
Classifier: Programming Language :: Python :: 2.7
Classifier: Programming Language :: Python :: 3.6
Classifier: Programming Language :: Python :: 3.7
Classifier: Programming Language :: JavaScript
Classifier: Topic :: Internet :: WWW/HTTP :: WSGI :: Application
